factorial_tb/__init__.py
factorial_tb/factorial.py
factorial_tb-0.0.1.dist-info/LICENSE
factorial_tb-0.0.1.dist-info/METADATA
factorial_tb-0.0.1.dist-info/WHEEL
factorial_tb-0.0.1.dist-info/top_level.txt
factorial_tb-0.0.1.dist-info/RECORD
